{
	"configurations" : 
	[
		{
			"directories" : 
			[
				{
					"build" : ".",
					"jsonFile" : "directory-.-Debug-f5ebdc15457944623624.json",
					"minimumCMakeVersion" : 
					{
						"string" : "3.26"
					},
					"projectIndex" : 0,
					"source" : ".",
					"targetIndexes" : 
					[
						0
					]
				}
			],
			"name" : "Debug",
			"projects" : 
			[
				{
					"directoryIndexes" : 
					[
						0
					],
					"name" : "no_213",
					"targetIndexes" : 
					[
						0
					]
				}
			],
			"targets" : 
			[
				{
					"directoryIndex" : 0,
					"id" : "no_213::@6890427a1f51a3e7e1df",
					"jsonFile" : "target-no_213-Debug-fba1e918db4688fa8bfe.json",
					"name" : "no_213",
					"projectIndex" : 0
				}
			]
		}
	],
	"kind" : "codemodel",
	"paths" : 
	{
		"build" : "/Users/xupeng/Documents/leetcode_library/no_213/cmake-build-debug",
		"source" : "/Users/xupeng/Documents/leetcode_library/no_213"
	},
	"version" : 
	{
		"major" : 2,
		"minor" : 5
	}
}
